{
	"animations": [
		{
			"offsets": [0, 0],
			"loop": false,
			"fps": 24,
			"anim": "idle",
			"indices": [],
			"name": "idle"
		},
		{
			"offsets": [0, 0],
			"loop": false,
			"fps": 24,
			"anim": "singUP",
			"indices": [],
			"name": "up"
		},
		{
			"offsets": [0, 0],
			"loop": false,
			"fps": 24,
			"anim": "singRIGHT",
			"indices": [],
			"name": "right"
		},
		{
			"offsets": [0, 0],
			"loop": false,
			"fps": 24,
			"anim": "singLEFT",
			"indices": [],
			"name": "left"
		},
		{
			"offsets": [0, 0],
			"loop": false,
			"fps": 24,
			"anim": "singDOWN",
			"indices": [],
			"name": "down"
		},
		{
			"offsets": [0, 0],
			"loop": false,
			"fps": 24,
			"anim": "fudido",
			"indices": [],
			"name": "fudido"
		},
		{
			"loop": false,
			"offsets": [0, 0],
			"anim": "alt-UP",
			"fps": 24,
			"name": "fudido",
			"indices": []
		}
	],
	"vocals_file": "",
	"no_antialiasing": true,
	"image": "characters/pao",
	"position": [-310, -670],
	"healthicon": "pao",
	"flip_x": false,
	"healthbar_colors": [255, 164, 46],
	"camera_position": [80, 600],
	"sing_duration": 4,
	"scale": 0.5,
	"_editor_isPlayer": false
}